{
    "ARCH":"DESKTOP_WIN_32",
    "BUILD TYPE":"Nightly",
    "Products":[
        {
            "Name":"Actor Framework",
            "Version":"3.1.1.0"
        },
        {
            "Name":"Classic Tools",
            "Version":"2.0.0.3"
        },
        {
            "Name":"Databox",
            "Version":"5.1.0.6"
        },
        {
            "Name":"Graph Actor",
            "Version":"1.1.1.10"
        },
        {
            "Name":"JSON",
            "Version":"4.2.1.10"
        },
        {
            "Name":"UI_Actor",
            "Version":"1.2.1.5"
        },
        {
            "Name":"Window Toolkit",
            "Version":"1.2.0.0"
        },
        {
            "Name":"treetk",
            "Version":"1.0.0.10"
        }
    ]
}